{"LIMBANGAN":["51383"],"SINGOROJO":["51382"],"KALIWUNGU+SELATAN":["51382","51372"],"BOJA":["51381"],"KALIWUNGU":["51372"],"BRANGSONG":["51371"],"PATEAN":["51364"],"SUKOREJO":["51363"],"PLANTUNGAN":["51362"],"PAGERRUYUNG":["51361"],"NGAMPEL":["51357"],"PEGANDON":["51357"],"RINGINARUM":["51356"],"GEMUH":["51356"],"WELERI":["51355"],"ROWOSARI":{"0":"51354","2":"51319"},"KANGKUNG":["51353"],"CEPIRING":["51352"],"PATEBON":["51351"],"KENDAL":{"0":"51319","2":"51318","3":"51317","4":"51316","5":"51315","6":"51313","7":"51314","8":"51312","9":"51311"}}