{"KASEMBON":["65393"],"NGANTANG":["65392"],"PUJON":["65391"],"LAWANG":{"0":"65216","2":"65215","3":"65214","4":"65213","5":"65211"},"AMPELGADING":["65183"],"TIRTOYUDO":["65182","65183"],"DAMPIT":["65181"],"BANTUR":["65179"],"GEDANGAN":["65178"],"SUMBERMANJING+WETAN":["65176"],"TUREN":["65175"],"GONDANGLEGI":["65174"],"PAGELARAN":["65174"],"WAJAK":["65173"],"TAJINAN":["65172"],"BULULAWANG":["65171"],"PAGAK":["65168"],"DONOMULYO":["65167"],"KALIPARE":["65166"],"SUMBERPUCUNG":["65165"],"KROMENGAN":["65165"],"WONOSARI":["65164"],"NGAJUNG+(NGAJUM)":["65164"],"KEPANJEN":["65163"],"PAKISAJI":["65162"],"WAGIR":["65158"],"PONCOKUSUMO":["65157"],"TUMPANG":["65156"],"JABUNG":["65155"],"PAKIS":["65154"],"SINGOSARI":["65153"],"KARANGPLOSO":["65152"],"DAU":["65151"],"SUKUN":{"0":"65149","2":"65148","3":"65147","4":"65146"},"LOWOKWARU":{"0":"65145","2":"65144","3":"65143","4":"65141","5":"65142"},"KEDUNGKANDANG":{"0":"65139","1":"65138","3":"65137","4":"65135","5":"65136","6":"65134","7":"65132","8":"65133"},"BLIMBING":["65137","65126","65125","65124","65121","65122","65123"],"KLOJEN":{"0":"65119","2":"65118","3":"65117","4":"65116","5":"65112","6":"65113","7":"65115","8":"65111"}}